{"map": 1, "virus": {"infectivity": {"underFive": 0.01, "fiveToSeventeen": 0.02, "eighteenToTwentyNine": 0.04, "thirtyToThirtyNine": 0.04, "fourtyToFourtyNine": 0.04, "fiftyToSixtyFour": 0.04, "sixtyFiveToSeventyFour": 0.02, "seventyFiveToEightyFour": 0.02, "overEightyFive": 0.04}, "fatality": {"underFive": 0.0001, "fiveToSeventeen": 0.0001, "eighteenToTwentyNine": 0.001, "thirtyToThirtyNine": 0.0045, "fourtyToFourtyNine": 0.013, "fiftyToSixtyFour": 0.044, "sixtyFiveToSeventyFour": 0.13, "seventyFiveToEightyFour": 0.32, "overEightyFive": 0.87}, "reinfectivity": {"underFive": 0.001, "fiveToSeventeen": 0.001, "eighteenToTwentyNine": 0.001, "thirtyToThirtyNine": 0.001, "fourtyToFourtyNine": 0.001, "fiftyToSixtyFour": 0.001, "sixtyFiveToSeventyFour": 0.001, "seventyFiveToEightyFour": 0.001, "overEightyFive": 0.001}, "symptomaticity": {"underFive": 0.5, "fiveToSeventeen": 0.5, "eighteenToTwentyNine": 0.5, "thirtyToThirtyNine": 0.5, "fourtyToFourtyNine": 0.5, "fiftyToSixtyFour": 0.5, "sixtyFiveToSeventyFour": 0.5, "seventyFiveToEightyFour": 0.5, "overEightyFive": 0.5}, "seriousRate": {"underFive": 0.02, "fiveToSeventeen": 0.01, "eighteenToTwentyNine": 0.06, "thirtyToThirtyNine": 0.1, "fourtyToFourtyNine": 0.15, "fiftyToSixtyFour": 0.25, "sixtyFiveToSeventyFour": 0.4, "seventyFiveToEightyFour": 0.65, "overEightyFive": 0.95}}, "nodes": [{"population": 82792351, "interactivity": {"underFive": 9.414, "fiveToSeventeen": 9.414, "eighteenToTwentyNine": 9.414, "thirtyToThirtyNine": 9.414, "fourtyToFourtyNine": 9.414, "fiftyToSixtyFour": 9.414, "sixtyFiveToSeventyFour": 9.414, "seventyFiveToEightyFour": 9.414, "overEightyFive": 9.414}, "name": "Germany", "position": {"x": 13.25, "y": 52.3}, "demographics": {"underFive": 0.046, "fiveToSeventeen": 0.117, "eighteenToTwentyNine": 0.14, "thirtyToThirtyNine": 0.126, "fourtyToFourtyNine": 0.13, "fiftyToSixtyFour": 0.226, "sixtyFiveToSeventyFour": 0.101, "seventyFiveToEightyFour": 0.086, "overEightyFive": 0.027}, "gdp": 3693204332230, "testingCapacity": 237713}, {"population": 66273576, "interactivity": {"underFive": 9.614, "fiveToSeventeen": 9.614, "eighteenToTwentyNine": 9.614, "thirtyToThirtyNine": 9.614, "fourtyToFourtyNine": 9.614, "fiftyToSixtyFour": 9.614, "sixtyFiveToSeventyFour": 9.614, "seventyFiveToEightyFour": 9.614, "overEightyFive": 9.614}, "name": "UK", "position": {"x": -0.05, "y": 51.36}, "demographics": {"underFive": 0.06, "fiveToSeventeen": 0.152, "eighteenToTwentyNine": 0.155, "thirtyToThirtyNine": 0.132, "fourtyToFourtyNine": 0.129, "fiftyToSixtyFour": 0.189, "sixtyFiveToSeventyFour": 0.1, "seventyFiveToEightyFour": 0.058, "overEightyFive": 0.024}, "gdp": 2637866340434, "testingCapacity": 1410000}, {"population": 67026224, "interactivity": {"underFive": 8.812, "fiveToSeventeen": 8.812, "eighteenToTwentyNine": 8.812, "thirtyToThirtyNine": 8.812, "fourtyToFourtyNine": 8.812, "fiftyToSixtyFour": 8.812, "sixtyFiveToSeventyFour": 8.812, "seventyFiveToEightyFour": 8.812, "overEightyFive": 8.812}, "name": "France", "position": {"x": 2.2, "y": 48.5}, "demographics": {"underFive": 0.057, "fiveToSeventeen": 0.163, "eighteenToTwentyNine": 0.137, "thirtyToThirtyNine": 0.124, "fourtyToFourtyNine": 0.131, "fiftyToSixtyFour": 0.192, "sixtyFiveToSeventyFour": 0.104, "seventyFiveToEightyFour": 0.06, "overEightyFive": 0.032}, "gdp": 2582501307216, "testingCapacity": 530564}, {"population": 60483973, "interactivity": {"underFive": 9.258, "fiveToSeventeen": 9.258, "eighteenToTwentyNine": 9.258, "thirtyToThirtyNine": 9.258, "fourtyToFourtyNine": 9.258, "fiftyToSixtyFour": 9.258, "sixtyFiveToSeventyFour": 9.258, "seventyFiveToEightyFour": 9.258, "overEightyFive": 9.258}, "name": "Italy", "position": {"x": 12.29, "y": 41.54}, "demographics": {"underFive": 0.04, "fiveToSeventeen": 0.122, "eighteenToTwentyNine": 0.122, "thirtyToThirtyNine": 0.119, "fourtyToFourtyNine": 0.156, "fiftyToSixtyFour": 0.215, "sixtyFiveToSeventyFour": 0.11, "seventyFiveToEightyFour": 0.081, "overEightyFive": 0.035}, "gdp": 1943835376342, "testingCapacity": 329462}, {"population": 46658447, "interactivity": {"underFive": 8.581, "fiveToSeventeen": 8.581, "eighteenToTwentyNine": 8.581, "thirtyToThirtyNine": 8.581, "fourtyToFourtyNine": 8.581, "fiftyToSixtyFour": 8.581, "sixtyFiveToSeventyFour": 8.581, "seventyFiveToEightyFour": 8.581, "overEightyFive": 8.581}, "name": "Spain", "position": {"x": -3.45, "y": 40.25}, "demographics": {"underFive": 0.045, "fiveToSeventeen": 0.134, "eighteenToTwentyNine": 0.121, "thirtyToThirtyNine": 0.138, "fourtyToFourtyNine": 0.166, "fiftyToSixtyFour": 0.204, "sixtyFiveToSeventyFour": 0.097, "seventyFiveToEightyFour": 0.063, "overEightyFive": 0.031}, "gdp": 1314314164402, "testingCapacity": 257295}, {"population": 17181084, "interactivity": {"underFive": 10.112, "fiveToSeventeen": 10.112, "eighteenToTwentyNine": 10.112, "thirtyToThirtyNine": 10.112, "fourtyToFourtyNine": 10.112, "fiftyToSixtyFour": 10.112, "sixtyFiveToSeventyFour": 10.112, "seventyFiveToEightyFour": 10.112, "overEightyFive": 10.112}, "name": "Netherlands", "position": {"x": 4.54, "y": 52.23}, "demographics": {"underFive": 0.051, "fiveToSeventeen": 0.147, "eighteenToTwentyNine": 0.151, "thirtyToThirtyNine": 0.121, "fourtyToFourtyNine": 0.134, "fiftyToSixtyFour": 0.208, "sixtyFiveToSeventyFour": 0.109, "seventyFiveToEightyFour": 0.058, "overEightyFive": 0.022}, "gdp": 830572618850, "testingCapacity": 42289}, {"population": 11398589, "interactivity": {"underFive": 9.959, "fiveToSeventeen": 9.959, "eighteenToTwentyNine": 9.959, "thirtyToThirtyNine": 9.959, "fourtyToFourtyNine": 9.959, "fiftyToSixtyFour": 9.959, "sixtyFiveToSeventyFour": 9.959, "seventyFiveToEightyFour": 9.959, "overEightyFive": 9.959}, "name": "Belgium", "position": {"x": 4.21, "y": 50.51}, "demographics": {"underFive": 0.055, "fiveToSeventeen": 0.148, "eighteenToTwentyNine": 0.147, "thirtyToThirtyNine": 0.13, "fourtyToFourtyNine": 0.133, "fiftyToSixtyFour": 0.201, "sixtyFiveToSeventyFour": 0.098, "seventyFiveToEightyFour": 0.06, "overEightyFive": 0.028}, "gdp": 494763551891, "testingCapacity": 68417}, {"population": 10741165, "interactivity": {"underFive": 8.481, "fiveToSeventeen": 8.481, "eighteenToTwentyNine": 8.481, "thirtyToThirtyNine": 8.481, "fourtyToFourtyNine": 8.481, "fiftyToSixtyFour": 8.481, "sixtyFiveToSeventyFour": 8.481, "seventyFiveToEightyFour": 8.481, "overEightyFive": 8.481}, "name": "Greece", "position": {"x": 23.46, "y": 37.58}, "demographics": {"underFive": 0.044, "fiveToSeventeen": 0.131, "eighteenToTwentyNine": 0.125, "thirtyToThirtyNine": 0.132, "fourtyToFourtyNine": 0.151, "fiftyToSixtyFour": 0.2, "sixtyFiveToSeventyFour": 0.107, "seventyFiveToEightyFour": 0.078, "overEightyFive": 0.033}, "gdp": 203085551429, "testingCapacity": 63255}, {"population": 10291027, "interactivity": {"underFive": 8.729, "fiveToSeventeen": 8.729, "eighteenToTwentyNine": 8.729, "thirtyToThirtyNine": 8.729, "fourtyToFourtyNine": 8.729, "fiftyToSixtyFour": 8.729, "sixtyFiveToSeventyFour": 8.729, "seventyFiveToEightyFour": 8.729, "overEightyFive": 8.729}, "name": "Portugal", "position": {"x": -9.1, "y": 38.42}, "demographics": {"underFive": 0.041, "fiveToSeventeen": 0.129, "eighteenToTwentyNine": 0.127, "thirtyToThirtyNine": 0.126, "fourtyToFourtyNine": 0.153, "fiftyToSixtyFour": 0.207, "sixtyFiveToSeventyFour": 0.111, "seventyFiveToEightyFour": 0.075, "overEightyFive": 0.029}, "gdp": 219308128887, "testingCapacity": 73839}, {"population": 10120242, "interactivity": {"underFive": 7.72, "fiveToSeventeen": 7.72, "eighteenToTwentyNine": 7.72, "thirtyToThirtyNine": 7.72, "fourtyToFourtyNine": 7.72, "fiftyToSixtyFour": 7.72, "sixtyFiveToSeventyFour": 7.72, "seventyFiveToEightyFour": 7.72, "overEightyFive": 7.72}, "name": "Sweden", "position": {"x": 18.03, "y": 59.2}, "demographics": {"underFive": 0.059, "fiveToSeventeen": 0.15, "eighteenToTwentyNine": 0.155, "thirtyToThirtyNine": 0.128, "fourtyToFourtyNine": 0.128, "fiftyToSixtyFour": 0.181, "sixtyFiveToSeventyFour": 0.11, "seventyFiveToEightyFour": 0.062, "overEightyFive": 0.026}, "gdp": 535607385506, "testingCapacity": 51085}, {"population": 9778371, "interactivity": {"underFive": 8.679, "fiveToSeventeen": 8.679, "eighteenToTwentyNine": 8.679, "thirtyToThirtyNine": 8.679, "fourtyToFourtyNine": 8.679, "fiftyToSixtyFour": 8.679, "sixtyFiveToSeventyFour": 8.679, "seventyFiveToEightyFour": 8.679, "overEightyFive": 8.679}, "name": "Hungary", "position": {"x": 19.05, "y": 47.29}, "demographics": {"underFive": 0.048, "fiveToSeventeen": 0.128, "eighteenToTwentyNine": 0.143, "thirtyToThirtyNine": 0.135, "fourtyToFourtyNine": 0.159, "fiftyToSixtyFour": 0.197, "sixtyFiveToSeventyFour": 0.109, "seventyFiveToEightyFour": 0.061, "overEightyFive": 0.02}, "gdp": 139761138103, "testingCapacity": 35140}, {"population": 8822267, "interactivity": {"underFive": 8.688, "fiveToSeventeen": 8.688, "eighteenToTwentyNine": 8.688, "thirtyToThirtyNine": 8.688, "fourtyToFourtyNine": 8.688, "fiftyToSixtyFour": 8.688, "sixtyFiveToSeventyFour": 8.688, "seventyFiveToEightyFour": 8.688, "overEightyFive": 8.688}, "name": "Austria", "position": {"x": 16.22, "y": 48.12}, "demographics": {"underFive": 0.049, "fiveToSeventeen": 0.125, "eighteenToTwentyNine": 0.151, "thirtyToThirtyNine": 0.135, "fourtyToFourtyNine": 0.14, "fiftyToSixtyFour": 0.214, "sixtyFiveToSeventyFour": 0.094, "seventyFiveToEightyFour": 0.067, "overEightyFive": 0.025}, "gdp": 416835975862, "testingCapacity": 526470}, {"population": 7050034, "interactivity": {"underFive": 8.296, "fiveToSeventeen": 8.296, "eighteenToTwentyNine": 8.296, "thirtyToThirtyNine": 8.296, "fourtyToFourtyNine": 8.296, "fiftyToSixtyFour": 8.296, "sixtyFiveToSeventyFour": 8.296, "seventyFiveToEightyFour": 8.296, "overEightyFive": 8.296}, "name": "Bulgaria", "position": {"x": 23.2, "y": 42.45}, "demographics": {"underFive": 0.046, "fiveToSeventeen": 0.123, "eighteenToTwentyNine": 0.127, "thirtyToThirtyNine": 0.139, "fourtyToFourtyNine": 0.151, "fiftyToSixtyFour": 0.203, "sixtyFiveToSeventyFour": 0.123, "seventyFiveToEightyFour": 0.068, "overEightyFive": 0.019}, "gdp": 58220973783, "testingCapacity": 16533}, {"population": 5781190, "interactivity": {"underFive": 8.89, "fiveToSeventeen": 8.89, "eighteenToTwentyNine": 8.89, "thirtyToThirtyNine": 8.89, "fourtyToFourtyNine": 8.89, "fiftyToSixtyFour": 8.89, "sixtyFiveToSeventyFour": 8.89, "seventyFiveToEightyFour": 8.89, "overEightyFive": 8.89}, "name": "Denmark", "position": {"x": 12.34, "y": 55.41}, "demographics": {"underFive": 0.052, "fiveToSeventeen": 0.15, "eighteenToTwentyNine": 0.159, "thirtyToThirtyNine": 0.117, "fourtyToFourtyNine": 0.133, "fiftyToSixtyFour": 0.196, "sixtyFiveToSeventyFour": 0.112, "seventyFiveToEightyFour": 0.06, "overEightyFive": 0.021}, "gdp": 329865537183, "testingCapacity": 195901}, {"population": 5513130, "interactivity": {"underFive": 7.561, "fiveToSeventeen": 7.561, "eighteenToTwentyNine": 7.561, "thirtyToThirtyNine": 7.561, "fourtyToFourtyNine": 7.561, "fiftyToSixtyFour": 7.561, "sixtyFiveToSeventyFour": 7.561, "seventyFiveToEightyFour": 7.561, "overEightyFive": 7.561}, "name": "Finland", "position": {"x": 25.03, "y": 60.15}, "demographics": {"underFive": 0.051, "fiveToSeventeen": 0.143, "eighteenToTwentyNine": 0.146, "thirtyToThirtyNine": 0.127, "fourtyToFourtyNine": 0.12, "fiftyToSixtyFour": 0.2, "sixtyFiveToSeventyFour": 0.123, "seventyFiveToEightyFour": 0.065, "overEightyFive": 0.027}, "gdp": 252301837573, "testingCapacity": 21721}, {"population": 5295619, "interactivity": {"underFive": 7.569, "fiveToSeventeen": 7.569, "eighteenToTwentyNine": 7.569, "thirtyToThirtyNine": 7.569, "fourtyToFourtyNine": 7.569, "fiftyToSixtyFour": 7.569, "sixtyFiveToSeventyFour": 7.569, "seventyFiveToEightyFour": 7.569, "overEightyFive": 7.569}, "name": "Norway", "position": {"x": 10.45, "y": 59.55}, "demographics": {"underFive": 0.057, "fiveToSeventeen": 0.157, "eighteenToTwentyNine": 0.16, "thirtyToThirtyNine": 0.134, "fourtyToFourtyNine": 0.139, "fiftyToSixtyFour": 0.185, "sixtyFiveToSeventyFour": 0.098, "seventyFiveToEightyFour": 0.049, "overEightyFive": 0.022}, "gdp": 399488897844, "testingCapacity": 29122}, {"population": 4830392, "interactivity": {"underFive": 8.374, "fiveToSeventeen": 8.374, "eighteenToTwentyNine": 8.374, "thirtyToThirtyNine": 8.374, "fourtyToFourtyNine": 8.374, "fiftyToSixtyFour": 8.374, "sixtyFiveToSeventyFour": 8.374, "seventyFiveToEightyFour": 8.374, "overEightyFive": 8.374}, "name": "Ireland", "position": {"x": -6.15, "y": 53.21}, "demographics": {"underFive": 0.066, "fiveToSeventeen": 0.181, "eighteenToTwentyNine": 0.145, "thirtyToThirtyNine": 0.152, "fourtyToFourtyNine": 0.146, "fiftyToSixtyFour": 0.171, "sixtyFiveToSeventyFour": 0.081, "seventyFiveToEightyFour": 0.043, "overEightyFive": 0.015}, "gdp": 331430014003, "testingCapacity": 26185}], "edges": [{"name": "Germany<->UK", "left": 0, "right": 1, "population": 51066, "interactivity": 10, "distance": 15572}, {"name": "Germany<->France", "left": 0, "right": 2, "population": 25566, "interactivity": 10, "distance": 16686}, {"name": "Germany<->Italy", "left": 0, "right": 3, "population": 9955, "interactivity": 10, "distance": 10046}, {"name": "Germany<->Spain", "left": 0, "right": 4, "population": 31644, "interactivity": 10, "distance": 2224}, {"name": "Germany<->Netherlands", "left": 0, "right": 5, "population": 16625, "interactivity": 10, "distance": 12235}, {"name": "Germany<->Belgium", "left": 0, "right": 6, "population": 5120, "interactivity": 10, "distance": 8897}, {"name": "Germany<->Greece", "left": 0, "right": 7, "population": 5782, "interactivity": 10, "distance": 10077}, {"name": "Germany<->Portugal", "left": 0, "right": 8, "population": 6697, "interactivity": 10, "distance": 8961}, {"name": "Germany<->Sweden", "left": 0, "right": 9, "population": 4168, "interactivity": 10, "distance": 18864}, {"name": "Germany<->Hungary", "left": 0, "right": 10, "population": 14274, "interactivity": 10, "distance": 11130}, {"name": "Germany<->Austria", "left": 0, "right": 11, "population": 16667, "interactivity": 10, "distance": 18892}, {"name": "Germany<->Bulgaria", "left": 0, "right": 12, "population": 298, "interactivity": 10, "distance": 8870}, {"name": "Germany<->Denmark", "left": 0, "right": 13, "population": 2305, "interactivity": 10, "distance": 12231}, {"name": "Germany<->Finland", "left": 0, "right": 14, "population": 5239, "interactivity": 10, "distance": 13362}, {"name": "Germany<->Norway", "left": 0, "right": 15, "population": 4402, "interactivity": 10, "distance": 7771}, {"name": "Germany<->Ireland", "left": 0, "right": 16, "population": 61025, "interactivity": 10, "distance": 15572}, {"name": "UK<->France", "left": 1, "right": 2, "population": 33205, "interactivity": 10, "distance": 1115}, {"name": "UK<->Italy", "left": 1, "right": 3, "population": 12930, "interactivity": 10, "distance": 5600}, {"name": "UK<->Spain", "left": 1, "right": 4, "population": 41099, "interactivity": 10, "distance": 17796}, {"name": "UK<->Netherlands", "left": 1, "right": 5, "population": 21593, "interactivity": 10, "distance": 12235}, {"name": "UK<->Belgium", "left": 1, "right": 6, "population": 6651, "interactivity": 10, "distance": 15571}, {"name": "UK<->Greece", "left": 1, "right": 7, "population": 7510, "interactivity": 10, "distance": 5638}, {"name": "UK<->Portugal", "left": 1, "right": 8, "population": 8698, "interactivity": 10, "distance": 6736}, {"name": "UK<->Sweden", "left": 1, "right": 9, "population": 5414, "interactivity": 10, "distance": 5548}, {"name": "UK<->Hungary", "left": 1, "right": 10, "population": 18540, "interactivity": 10, "distance": 4456}, {"name": "UK<->Austria", "left": 1, "right": 11, "population": 21648, "interactivity": 10, "distance": 5559}, {"name": "UK<->Bulgaria", "left": 1, "right": 12, "population": 387, "interactivity": 10, "distance": 15536}, {"name": "UK<->Denmark", "left": 1, "right": 13, "population": 2994, "interactivity": 10, "distance": 12229}, {"name": "UK<->Finland", "left": 1, "right": 14, "population": 6805, "interactivity": 10, "distance": 2272}, {"name": "UK<->Norway", "left": 1, "right": 15, "population": 5718, "interactivity": 10, "distance": 16650}, {"name": "UK<->Ireland", "left": 1, "right": 16, "population": 79259, "interactivity": 10, "distance": 70}, {"name": "France<->Italy", "left": 2, "right": 3, "population": 6473, "interactivity": 10, "distance": 6682}, {"name": "France<->Spain", "left": 2, "right": 4, "population": 20576, "interactivity": 10, "distance": 18909}, {"name": "France<->Netherlands", "left": 2, "right": 5, "population": 10810, "interactivity": 10, "distance": 11120}, {"name": "France<->Belgium", "left": 2, "right": 6, "population": 3329, "interactivity": 10, "distance": 14459}, {"name": "France<->Greece", "left": 2, "right": 7, "population": 3760, "interactivity": 10, "distance": 6695}, {"name": "France<->Portugal", "left": 2, "right": 8, "population": 4354, "interactivity": 10, "distance": 7803}, {"name": "France<->Sweden", "left": 2, "right": 9, "population": 2710, "interactivity": 10, "distance": 4434}, {"name": "France<->Hungary", "left": 2, "right": 10, "population": 9282, "interactivity": 10, "distance": 5561}, {"name": "France<->Austria", "left": 2, "right": 11, "population": 10838, "interactivity": 10, "distance": 4449}, {"name": "France<->Bulgaria", "left": 2, "right": 12, "population": 194, "interactivity": 10, "distance": 14452}, {"name": "France<->Denmark", "left": 2, "right": 13, "population": 1499, "interactivity": 10, "distance": 11114}, {"name": "France<->Finland", "left": 2, "right": 14, "population": 3407, "interactivity": 10, "distance": 3366}, {"name": "France<->Norway", "left": 2, "right": 15, "population": 2863, "interactivity": 10, "distance": 15547}, {"name": "France<->Ireland", "left": 2, "right": 16, "population": 39681, "interactivity": 10, "distance": 1119}, {"name": "Italy<->Spain", "left": 3, "right": 4, "population": 8012, "interactivity": 10, "distance": 12235}, {"name": "Italy<->Netherlands", "left": 3, "right": 5, "population": 4209, "interactivity": 10, "distance": 17510}, {"name": "Italy<->Belgium", "left": 3, "right": 6, "population": 1296, "interactivity": 10, "distance": 18589}, {"name": "Italy<->Greece", "left": 3, "right": 7, "population": 1464, "interactivity": 10, "distance": 413}, {"name": "Italy<->Portugal", "left": 3, "right": 8, "population": 1695, "interactivity": 10, "distance": 1161}, {"name": "Italy<->Sweden", "left": 3, "right": 9, "population": 1055, "interactivity": 10, "distance": 10979}, {"name": "Italy<->Hungary", "left": 3, "right": 10, "population": 3614, "interactivity": 10, "distance": 1253}, {"name": "Italy<->Austria", "left": 3, "right": 11, "population": 4220, "interactivity": 10, "distance": 11102}, {"name": "Italy<->Bulgaria", "left": 3, "right": 12, "population": 75, "interactivity": 10, "distance": 18905}, {"name": "Italy<->Denmark", "left": 3, "right": 13, "population": 583, "interactivity": 10, "distance": 17332}, {"name": "Italy<->Finland", "left": 3, "right": 14, "population": 1326, "interactivity": 10, "distance": 3719}, {"name": "Italy<->Norway", "left": 3, "right": 15, "population": 1114, "interactivity": 10, "distance": 17212}, {"name": "Italy<->Ireland", "left": 3, "right": 16, "population": 15452, "interactivity": 10, "distance": 5616}, {"name": "Spain<->Netherlands", "left": 4, "right": 5, "population": 13380, "interactivity": 10, "distance": 10010}, {"name": "Spain<->Belgium", "left": 4, "right": 6, "population": 4121, "interactivity": 10, "distance": 6673}, {"name": "Spain<->Greece", "left": 4, "right": 7, "population": 4654, "interactivity": 10, "distance": 12235}, {"name": "Spain<->Portugal", "left": 4, "right": 8, "population": 5390, "interactivity": 10, "distance": 11122}, {"name": "Spain<->Sweden", "left": 4, "right": 9, "population": 3355, "interactivity": 10, "distance": 16684}, {"name": "Spain<->Hungary", "left": 4, "right": 10, "population": 11488, "interactivity": 10, "distance": 13347}, {"name": "Spain<->Austria", "left": 4, "right": 11, "population": 13414, "interactivity": 10, "distance": 16684}, {"name": "Spain<->Bulgaria", "left": 4, "right": 12, "population": 240, "interactivity": 10, "distance": 6673}, {"name": "Spain<->Denmark", "left": 4, "right": 13, "population": 1855, "interactivity": 10, "distance": 10010}, {"name": "Spain<->Finland", "left": 4, "right": 14, "population": 4217, "interactivity": 10, "distance": 15572}, {"name": "Spain<->Norway", "left": 4, "right": 15, "population": 3543, "interactivity": 10, "distance": 5561}, {"name": "Spain<->Ireland", "left": 4, "right": 16, "population": 49115, "interactivity": 10, "distance": 17796}, {"name": "Netherlands<->Belgium", "left": 5, "right": 6, "population": 2165, "interactivity": 10, "distance": 3341}, {"name": "Netherlands<->Greece", "left": 5, "right": 7, "population": 2445, "interactivity": 10, "distance": 17283}, {"name": "Netherlands<->Portugal", "left": 5, "right": 8, "population": 2831, "interactivity": 10, "distance": 18131}, {"name": "Netherlands<->Sweden", "left": 5, "right": 9, "population": 1762, "interactivity": 10, "distance": 6700}, {"name": "Netherlands<->Hungary", "left": 5, "right": 10, "population": 6036, "interactivity": 10, "distance": 16643}, {"name": "Netherlands<->Austria", "left": 5, "right": 11, "population": 7048, "interactivity": 10, "distance": 6683}, {"name": "Netherlands<->Bulgaria", "left": 5, "right": 12, "population": 126, "interactivity": 10, "distance": 3493}, {"name": "Netherlands<->Denmark", "left": 5, "right": 13, "population": 974, "interactivity": 10, "distance": 353}, {"name": "Netherlands<->Finland", "left": 5, "right": 14, "population": 2215, "interactivity": 10, "distance": 14409}, {"name": "Netherlands<->Norway", "left": 5, "right": 15, "population": 1861, "interactivity": 10, "distance": 4510}, {"name": "Netherlands<->Ireland", "left": 5, "right": 16, "population": 25804, "interactivity": 10, "distance": 12234}, {"name": "Belgium<->Greece", "left": 6, "right": 7, "population": 753, "interactivity": 10, "distance": 18310}, {"name": "Belgium<->Portugal", "left": 6, "right": 8, "population": 872, "interactivity": 10, "distance": 17467}, {"name": "Belgium<->Sweden", "left": 6, "right": 9, "population": 542, "interactivity": 10, "distance": 10042}, {"name": "Belgium<->Hungary", "left": 6, "right": 10, "population": 1859, "interactivity": 10, "distance": 19711}, {"name": "Belgium<->Austria", "left": 6, "right": 11, "population": 2170, "interactivity": 10, "distance": 10013}, {"name": "Belgium<->Bulgaria", "left": 6, "right": 12, "population": 38, "interactivity": 10, "distance": 776}, {"name": "Belgium<->Denmark", "left": 6, "right": 13, "population": 300, "interactivity": 10, "distance": 3377}, {"name": "Belgium<->Finland", "left": 6, "right": 14, "population": 682, "interactivity": 10, "distance": 17654}, {"name": "Belgium<->Norway", "left": 6, "right": 15, "population": 573, "interactivity": 10, "distance": 1382}, {"name": "Belgium<->Ireland", "left": 6, "right": 16, "population": 7948, "interactivity": 10, "distance": 15568}, {"name": "Greece<->Portugal", "left": 7, "right": 8, "population": 984, "interactivity": 10, "distance": 1115}, {"name": "Greece<->Sweden", "left": 7, "right": 9, "population": 613, "interactivity": 10, "distance": 10909}, {"name": "Greece<->Hungary", "left": 7, "right": 10, "population": 2099, "interactivity": 10, "distance": 1480}, {"name": "Greece<->Austria", "left": 7, "right": 11, "population": 2451, "interactivity": 10, "distance": 11071}, {"name": "Greece<->Bulgaria", "left": 7, "right": 12, "population": 43, "interactivity": 10, "distance": 18805}, {"name": "Greece<->Denmark", "left": 7, "right": 13, "population": 339, "interactivity": 10, "distance": 17068}, {"name": "Greece<->Finland", "left": 7, "right": 14, "population": 770, "interactivity": 10, "distance": 3886}, {"name": "Greece<->Norway", "left": 7, "right": 15, "population": 647, "interactivity": 10, "distance": 16968}, {"name": "Greece<->Ireland", "left": 7, "right": 16, "population": 8975, "interactivity": 10, "distance": 5659}, {"name": "Portugal<->Sweden", "left": 8, "right": 9, "population": 710, "interactivity": 10, "distance": 12019}, {"name": "Portugal<->Hungary", "left": 8, "right": 10, "population": 2431, "interactivity": 10, "distance": 2407}, {"name": "Portugal<->Austria", "left": 8, "right": 11, "population": 2839, "interactivity": 10, "distance": 12187}, {"name": "Portugal<->Bulgaria", "left": 8, "right": 12, "population": 50, "interactivity": 10, "distance": 17757}, {"name": "Portugal<->Denmark", "left": 8, "right": 13, "population": 392, "interactivity": 10, "distance": 17836}, {"name": "Portugal<->Finland", "left": 8, "right": 14, "population": 892, "interactivity": 10, "distance": 4878}, {"name": "Portugal<->Norway", "left": 8, "right": 15, "population": 749, "interactivity": 10, "distance": 16085}, {"name": "Portugal<->Ireland", "left": 8, "right": 16, "population": 10394, "interactivity": 10, "distance": 6755}, {"name": "Sweden<->Hungary", "left": 9, "right": 10, "population": 1513, "interactivity": 10, "distance": 9951}, {"name": "Sweden<->Austria", "left": 9, "right": 11, "population": 1767, "interactivity": 10, "distance": 615}, {"name": "Sweden<->Bulgaria", "left": 9, "right": 12, "population": 31, "interactivity": 10, "distance": 10127}, {"name": "Sweden<->Denmark", "left": 9, "right": 13, "population": 244, "interactivity": 10, "distance": 6681}, {"name": "Sweden<->Finland", "left": 9, "right": 14, "population": 555, "interactivity": 10, "distance": 7785}, {"name": "Sweden<->Norway", "left": 9, "right": 15, "population": 466, "interactivity": 10, "distance": 11123}, {"name": "Sweden<->Ireland", "left": 9, "right": 16, "population": 6470, "interactivity": 10, "distance": 5553}, {"name": "Hungary<->Austria", "left": 10, "right": 11, "population": 6051, "interactivity": 10, "distance": 10010}, {"name": "Hungary<->Bulgaria", "left": 10, "right": 12, "population": 108, "interactivity": 10, "distance": 19555}, {"name": "Hungary<->Denmark", "left": 10, "right": 13, "population": 837, "interactivity": 10, "distance": 16575}, {"name": "Hungary<->Finland", "left": 10, "right": 14, "population": 1902, "interactivity": 10, "distance": 2471}, {"name": "Hungary<->Norway", "left": 10, "right": 15, "population": 1598, "interactivity": 10, "distance": 18447}, {"name": "Hungary<->Ireland", "left": 10, "right": 16, "population": 22155, "interactivity": 10, "distance": 4464}, {"name": "Austria<->Bulgaria", "left": 11, "right": 12, "population": 126, "interactivity": 10, "distance": 10024}, {"name": "Austria<->Denmark", "left": 11, "right": 13, "population": 977, "interactivity": 10, "distance": 6703}, {"name": "Austria<->Finland", "left": 11, "right": 14, "population": 2221, "interactivity": 10, "distance": 7738}, {"name": "Austria<->Norway", "left": 11, "right": 15, "population": 1866, "interactivity": 10, "distance": 11172}, {"name": "Austria<->Ireland", "left": 11, "right": 16, "population": 25870, "interactivity": 10, "distance": 5555}, {"name": "Bulgaria<->Denmark", "left": 12, "right": 13, "population": 17, "interactivity": 10, "distance": 3608}, {"name": "Bulgaria<->Finland", "left": 12, "right": 14, "population": 39, "interactivity": 10, "distance": 17348}, {"name": "Bulgaria<->Norway", "left": 12, "right": 15, "population": 33, "interactivity": 10, "distance": 1908}, {"name": "Bulgaria<->Ireland", "left": 12, "right": 16, "population": 463, "interactivity": 10, "distance": 15520}, {"name": "Denmark<->Finland", "left": 13, "right": 14, "population": 307, "interactivity": 10, "distance": 14441}, {"name": "Denmark<->Norway", "left": 13, "right": 15, "population": 258, "interactivity": 10, "distance": 4468}, {"name": "Denmark<->Ireland", "left": 13, "right": 16, "population": 3578, "interactivity": 10, "distance": 12233}, {"name": "Finland<->Norway", "left": 14, "right": 15, "population": 586, "interactivity": 10, "distance": 18908}, {"name": "Finland<->Ireland", "left": 14, "right": 16, "population": 8132, "interactivity": 10, "distance": 2254}, {"name": "Norway<->Ireland", "left": 15, "right": 16, "population": 6833, "interactivity": 10, "distance": 16664}]}